validatorsdk/__init__.py
validatorsdk/utils.py
validatorsdk/validator.py
validatorsdk-0.2.0.dist-info/METADATA
validatorsdk-0.2.0.dist-info/WHEEL
validatorsdk-0.2.0.dist-info/top_level.txt
validatorsdk-0.2.0.dist-info/RECORD
