Metadata-Version: 2.1
Name: validatorsdk
Version: 0.2.0
Summary: Validator SDK
Home-page: UNKNOWN
Author: Topaz Bott
Author-email: topaz@topazhome.net
License: UNKNOWN
Platform: UNKNOWN
Classifier: Development Status :: 5 - Production/Stable
Classifier: Intended Audience :: Developers
Classifier: Natural Language :: English
Classifier: Programming Language :: Python
Classifier: Programming Language :: Python :: 3.8
Classifier: Programming Language :: Python :: 3.9
Classifier: Programming Language :: Python :: 3.10
Requires-Dist: urllib3
Requires-Dist: boto3
Requires-Dist: blinker
